peptide_matcher/__init__.py
peptide_matcher/gui.py
peptide_matcher/main.py
peptide_matcher/peptideMatcher.py
peptide_matcher/pmFrame.py
peptide_matcher/utils.py
peptide_matcher-2.0.0.dist-info/LICENSE
peptide_matcher-2.0.0.dist-info/METADATA
peptide_matcher-2.0.0.dist-info/WHEEL
peptide_matcher-2.0.0.dist-info/entry_points.txt
peptide_matcher-2.0.0.dist-info/top_level.txt
peptide_matcher-2.0.0.dist-info/RECORD
