Metadata-Version: 2.1
Name: peptide-matcher
Version: 2.0.0
Summary: Peptide matcher
Author-email: Andrey Rozenberg <alephreish@gmail.com>
Project-URL: Homepage, https://github.com/OKLAB2016/peptide-matcher
Project-URL: Bug Tracker, https://github.com/OKLAB2016/peptide-matcher/issues
Classifier: Programming Language :: Python :: 3
Classifier: License :: OSI Approved :: GNU General Public License v3 (GPLv3)
Classifier: Operating System :: OS Independent
Requires-Python: >=3.7
License-File: LICENSE
Requires-Dist: wxPython
Requires-Dist: xlsxwriter
Requires-Dist: pyahocorasick
Requires-Dist: biopython
